ovos_plugin_mplayer/__init__.py
ovos_plugin_mplayer/version.py
ovos_plugin_mplayer-0.0.0.dist-info/LICENSE
ovos_plugin_mplayer-0.0.0.dist-info/METADATA
ovos_plugin_mplayer-0.0.0.dist-info/WHEEL
ovos_plugin_mplayer-0.0.0.dist-info/entry_points.txt
ovos_plugin_mplayer-0.0.0.dist-info/top_level.txt
ovos_plugin_mplayer-0.0.0.dist-info/RECORD
