Metadata-Version: 2.1
Name: ovos-plugin-mplayer
Version: 0.0.0
Summary: mplayer plugin for ovos
Home-page: https://github.com/OpenVoiceOS/ovos-mplayer-plugin
Author: JarbasAi
Author-email: jarbasai@mailfence.com
License: Apache-2.0
Keywords: ovos audio plugin
Platform: UNKNOWN
Requires-Dist: ovos-plugin-manager
Requires-Dist: ovos-plugin-common-play
Requires-Dist: py-mplayer
